control_unit.v
module control_unit (
    input  wire       clk,
    input  wire       reset,
    input  wire [2:0] opcode,
    input  wire       zero,

    output reg        pc_en,
    output reg        ir_en,
    output reg        reg_we,
    output reg        mem_we,
    output reg [2:0]  alu_op,
    output reg [1:0]  state
);

    // FSM states
    localparam FETCH  = 2'd0;
    localparam DECODE = 2'd1;
    localparam EXEC   = 2'd2;
    localparam WB     = 2'd3;

    // ========================
    // State register
    // ========================
    always @(posedge clk or posedge reset) begin
        if (reset)
            state <= FETCH;
        else begin
            case (state)
                FETCH:  state <= DECODE;
                DECODE: state <= EXEC;
                EXEC:   state <= WB;
                WB:     state <= FETCH;
                default: state <= FETCH;
            endcase
        end
    end

    // ========================
    // Control logic
    // ========================
    always @(*) begin
        // defaults
        pc_en   = 0;
        ir_en   = 0;
        reg_we  = 0;
        mem_we  = 0;
        alu_op  = 3'b000;

        case (state)

            // ----------------
            FETCH: begin
                pc_en = 1;
                ir_en = 1;
            end

            // ----------------
            EXEC: begin
                case (opcode)
                    3'b000, // ADD
                    3'b001, // SUB
                    3'b010, // AND
                    3'b011: // OR
                        alu_op = opcode;

                    3'b101: // STORE
                        mem_we = 1;

                    default: ;
                endcase
            end

            // ----------------
            WB: begin
                case (opcode)
                    3'b000, // ADD
                    3'b001, // SUB
                    3'b010, // AND
                    3'b011, // OR
                    3'b100: // LOAD
                        reg_we = 1;

                    default: ;
                endcase
            end

            default: ;
        endcase
    end

endmodule

alu.v
module alu (
    input  wire [7:0] a,
    input  wire [7:0] b,
    input  wire [2:0] alu_op,
    output reg  [7:0] result,
    output wire       zero
);

always @(*) begin
    case (alu_op)
        3'b000: result = a + b;   // ADD
        3'b001: result = a - b;   // SUB
        3'b010: result = a & b;   // AND
        3'b011: result = a | b;   // OR
        default: result = 8'd0;
    endcase
end

assign zero = (result == 8'd0);

endmodule

reg_file.v
module reg_file (
    input  wire       clk,
    input  wire       we,
    input  wire [2:0] rd,
    input  wire [2:0] rs,
    input  wire [7:0] wd,
    output wire [7:0] rd_data,
    output wire [7:0] rs_data
);

reg [7:0] regs [0:7];

integer i;
initial begin
    for (i = 0; i < 8; i = i + 1)
        regs[i] = 8'd0;
    regs[1] = 8'd1;
end



assign rd_data = regs[rd];
assign rs_data = regs[rs];

always @(posedge clk) begin
    if (we)
        regs[rd] <= wd;
end

endmodule

instr_reg.v
module instr_reg (
    input  wire       clk,
    input  wire       ir_en,
    input  wire [7:0] instr_in,
    output reg  [7:0] instr
);

always @(posedge clk) begin
    if (ir_en)
        instr <= instr_in;
end

endmodule

instrt_mem.v
module instr_mem (
    input  wire [7:0] addr,
    output wire [7:0] instr
);

reg [7:0] mem [0:255];

initial begin
    // Program:
    // R1 = R1 + R1
    // MEM[R0] = R1
    // R2 = MEM[R0]
    // JMP 0

    mem[0] = 8'b000_001_01; // ADD   R1, R1
    mem[1] = 8'b101_001_00; // STORE R1, [R0]
    mem[2] = 8'b100_010_00; // LOAD  R2, [R0]
    mem[3] = 8'b110_000_00; // JMP 0
end

assign instr = mem[addr];

endmodule

pc.v
module pc (
    input  wire       clk,
    input  wire       reset,
    input  wire       pc_en,
    input  wire [7:0] pc_next,
    output reg  [7:0] pc
);

always @(posedge clk or posedge reset) begin
    if (reset)
        pc <= 8'd0;
    else if (pc_en)
        pc <= pc_next;
end

endmodule

cpu_top.v
module cpu_top (
    input wire clk,
    input wire reset
);

    // ========================
    // Wires
    // ========================
    wire [7:0] pc_out;
    wire [7:0] pc_next;

    wire [7:0] instr;
    wire [7:0] ir;

    wire [7:0] rd_data;
    wire [7:0] rs_data;
    wire [7:0] alu_out;

    wire zero;

    wire pc_en;
    wire ir_en;
    wire reg_we;
    wire mem_we;

    wire [2:0] alu_op;
    wire [1:0] state;
    wire [7:0] mem_rd;
wire [7:0] wb_data;


    // ========================
    // Instruction fields (ISA decode)
    // ========================
    wire [2:0] opcode = ir[7:5];      // what to do
    wire [2:0] rd     = ir[4:2];      // destination register
    wire [2:0] rs     = {1'b0, ir[1:0]}; // source register (zero-extended)

    // Write-back data select (LOAD vs ALU)
assign wb_data = (opcode == 3'b100) ? mem_rd : alu_out;


    // ========================
    // PC next logic (JMP support)
    // ========================
    // opcode 110 = JMP
    // jump target = ir[1:0] (0–3)
   assign pc_next =
    (state == 2'd0 && opcode == 3'b110) ? {6'd0, ir[1:0]} :
                                          pc_out + 8'd1;

    // ========================
    // Module instantiations
    // ========================

    // Program Counter
    pc PC (
        .clk     (clk),
        .reset   (reset),
        .pc_en   (pc_en),
        .pc_next (pc_next),
        .pc      (pc_out)
    );

    // Instruction Memory (ROM)
    instr_mem IM (
        .addr  (pc_out),
        .instr (instr)
    );

    // Instruction Register
    instr_reg IR (
        .clk      (clk),
        .ir_en    (ir_en),
        .instr_in (instr),
        .instr    (ir)
    );

    // Register File
    reg_file RF (
        .clk     (clk),
        .we      (reg_we),
        .rd      (rd),
        .rs      (rs),
        .wd      (wb_data),
        .rd_data (rd_data),
        .rs_data (rs_data)
    );

    // ALU
    alu ALU (
        .a      (rd_data),
        .b      (rs_data),
        .alu_op (alu_op),
        .result (alu_out),
        .zero   (zero)
    );

    // Control Unit (FSM)
    control_unit CU (
        .clk    (clk),
        .reset  (reset),
        .opcode (opcode),
        .zero   (zero),
        .pc_en  (pc_en),
        .ir_en  (ir_en),
        .reg_we (reg_we),
        .mem_we (mem_we),
        .alu_op (alu_op),
        .state  (state)
    );

endmodule

cpu_tb.v
module cpu_tb;

reg clk = 0;
reg reset = 1;

cpu_top DUT (
    .clk(clk),
    .reset(reset)
);

// Clock generation
always #5 clk = ~clk;

// VCD dump
initial begin
    $dumpfile("cpu.vcd");
    $dumpvars(0, cpu_tb);
end

// Reset + finish
initial begin
    #10 reset = 0;
    #300 $finish;
end

endmodule

cpu.vcd
$date
	Thu Jan 29 20:59:26 2026
$end
$version
	Icarus Verilog
$end
$timescale
	1s
$end
$scope module cpu_tb $end
$var reg 1 ! clk $end
$var reg 1 " reset $end
$scope module DUT $end
$var wire 3 # alu_op [2:0] $end
$var wire 8 $ alu_out [7:0] $end
$var wire 1 % clk $end
$var wire 8 & instr [7:0] $end
$var wire 8 ' ir [7:0] $end
$var wire 1 ( ir_en $end
$var wire 8 ) mem_rd [7:0] $end
$var wire 1 * mem_we $end
$var wire 3 + opcode [2:0] $end
$var wire 1 , pc_en $end
$var wire 8 - pc_next [7:0] $end
$var wire 8 . pc_out [7:0] $end
$var wire 3 / rd [2:0] $end
$var wire 8 0 rd_data [7:0] $end
$var wire 1 1 reg_we $end
$var wire 1 2 reset $end
$var wire 3 3 rs [2:0] $end
$var wire 8 4 rs_data [7:0] $end
$var wire 2 5 state [1:0] $end
$var wire 8 6 wb_data [7:0] $end
$var wire 1 7 zero $end
$scope module PC $end
$var wire 1 % clk $end
$var wire 1 , pc_en $end
$var wire 8 8 pc_next [7:0] $end
$var wire 1 2 reset $end
$var reg 8 9 pc [7:0] $end
$upscope $end
$scope module IM $end
$var wire 8 : addr [7:0] $end
$var wire 8 ; instr [7:0] $end
$upscope $end
$scope module IR $end
$var wire 1 % clk $end
$var wire 8 < instr_in [7:0] $end
$var wire 1 ( ir_en $end
$var reg 8 = instr [7:0] $end
$upscope $end
$scope module RF $end
$var wire 1 % clk $end
$var wire 3 > rd [2:0] $end
$var wire 8 ? rd_data [7:0] $end
$var wire 3 @ rs [2:0] $end
$var wire 8 A rs_data [7:0] $end
$var wire 8 B wd [7:0] $end
$var wire 1 1 we $end
$var integer 32 C i [31:0] $end
$upscope $end
$scope module ALU $end
$var wire 8 D a [7:0] $end
$var wire 3 E alu_op [2:0] $end
$var wire 8 F b [7:0] $end
$var wire 1 7 zero $end
$var reg 8 G result [7:0] $end
$upscope $end
$scope module CU $end
$var wire 1 % clk $end
$var wire 3 H opcode [2:0] $end
$var wire 1 2 reset $end
$var wire 1 7 zero $end
$var reg 3 I alu_op [2:0] $end
$var reg 1 J ir_en $end
$var reg 1 K mem_we $end
$var reg 1 L pc_en $end
$var reg 1 M reg_we $end
$var reg 2 N state [1:0] $end
$upscope $end
$upscope $end
$upscope $end
$enddefinitions $end
#0
$dumpvars
b0 N
0M
1L
0K
1J
b0 I
bx H
bx G
bx F
b0 E
bx D
b1000 C
bx B
bx A
b0xx @
bx ?
bx >
bx =
b101 <
b101 ;
b0 :
b0 9
b0xx 8
x7
bx 6
b0 5
bx 4
b0xx 3
12
01
bx 0
bx /
b0 .
b0xx -
1,
bx +
0*
bz )
1(
bx '
b101 &
0%
bx $
b0 #
1"
0!
$end
#5
b10 6
b10 B
b1 -
b1 8
b10 G
07
b10 $
1J
1(
1L
1,
b1 4
b1 A
b1 F
b1 3
b1 @
b1 0
b1 ?
b1 D
b1 /
b1 >
b0 +
b0 H
b101 =
b101 '
1!
1%
#10
0!
0%
0"
02
#15
b10 -
b10 8
0J
0(
0L
0,
b1 9
b10100100 &
b10100100 ;
b10100100 <
b1 .
b1 :
b1 N
b1 5
1!
1%
#20
0!
0%
#25
b10 N
b10 5
1!
1%
#30
0!
0%
#35
1M
11
b11 N
b11 5
1!
1%
#40
0!
0%
#45
b100 6
b100 B
1J
1(
1L
1,
0M
01
b100 G
b100 $
b0 N
b0 5
b10 0
b10 ?
b10 D
b10 4
b10 A
b10 F
1!
1%
#50
0!
0%
#55
b10 6
b10 B
b10 G
b10 $
b11 -
b11 8
0J
0(
0L
0,
b0 4
b0 A
b0 F
b0 3
b0 @
b101 +
b101 H
b10 9
b10001000 &
b10001000 ;
b10001000 <
b10 .
b10 :
b1 N
b1 5
b10100100 =
b10100100 '
1!
1%
#60
0!
0%
#65
1K
1*
b10 N
b10 5
1!
1%
#70
0!
0%
#75
0K
0*
b11 N
b11 5
1!
1%
#80
0!
0%
#85
1J
1(
1L
1,
b0 N
b0 5
1!
1%
#90
0!
0%
#95
b0 G
17
b0 $
bz 6
bz B
b100 -
b100 8
0J
0(
0L
0,
b0 0
b0 ?
b0 D
b10 /
b10 >
b100 +
b100 H
b11 9
b11000000 &
b11000000 ;
b11000000 <
b11 .
b11 :
b1 N
b1 5
b10001000 =
b10001000 '
1!
1%
#100
0!
0%
#105
b10 N
b10 5
1!
1%
#110
0!
0%
#115
1M
11
b11 N
b11 5
1!
1%
#120
0!
0%
#125
1J
1(
1L
1,
0M
01
bx G
x7
bx $
b0 N
b0 5
bz 0
bz ?
bz D
1!
1%
#130
0!
0%
#135
b0 G
17
b0 $
b0 6
b0 B
b101 -
b101 8
0J
0(
0L
0,
b0 0
b0 ?
b0 D
b0 /
b0 >
b110 +
b110 H
b100 9
bx &
bx ;
bx <
b100 .
b100 :
b1 N
b1 5
b11000000 =
b11000000 '
1!
1%
#140
0!
0%
#145
b10 N
b10 5
1!
1%
#150
0!
0%
#155
b11 N
b11 5
1!
1%
#160
0!
0%
#165
b0 -
b0 8
1J
1(
1L
1,
b0 N
b0 5
1!
1%
#170
0!
0%
#175
b1 -
b1 8
bx G
x7
bx $
bx 6
bx B
0J
0(
0L
0,
bx 4
bx A
bx F
b0xx 3
b0xx @
bx 0
bx ?
bx D
bx /
bx >
bx +
bx H
b0 9
b101 &
b101 ;
b101 <
b0 .
b0 :
b1 N
b1 5
bx =
bx '
1!
1%
#180
0!
0%
#185
b10 N
b10 5
1!
1%
#190
0!
0%
#195
b11 N
b11 5
1!
1%
#200
0!
0%
#205
b0xx -
b0xx 8
1J
1(
1L
1,
b0 N
b0 5
1!
1%
#210
0!
0%
#215
b100 6
b100 B
b100 G
07
b100 $
bx -
bx 8
0J
0(
0L
0,
b10 4
b10 A
b10 F
b1 3
b1 @
b10 0
b10 ?
b10 D
b1 /
b1 >
b0 +
b0 H
b0xx 9
bx &
bx ;
bx <
b0xx .
b0xx :
b1 N
b1 5
b101 =
b101 '
1!
1%
#220
0!
0%
#225
b10 N
b10 5
1!
1%
#230
0!
0%
#235
1M
11
b11 N
b11 5
1!
1%
#240
0!
0%
#245
b1000 6
b1000 B
1J
1(
1L
1,
0M
01
b1000 G
b1000 $
b0 N
b0 5
b100 0
b100 ?
b100 D
b100 4
b100 A
b100 F
1!
1%
#250
0!
0%
#255
bx G
x7
bx $
bx 6
bx B
0J
0(
0L
0,
bx 4
bx A
bx F
b0xx 3
b0xx @
bx 0
bx ?
bx D
bx /
bx >
bx +
bx H
bx 9
bx .
bx :
b1 N
b1 5
bx =
bx '
1!
1%
#260
0!
0%
#265
b10 N
b10 5
1!
1%
#270
0!
0%
#275
b11 N
b11 5
1!
1%
#280
0!
0%
#285
1J
1(
1L
1,
b0 N
b0 5
1!
1%
#290
0!
0%
#295
0J
0(
0L
0,
b1 N
b1 5
1!
1%
#300
0!
0%
#305
b10 N
b10 5
1!
1%
